sigr/__init__.py
sigr/_modidx.py
sigr/attr.py
sigr/bcls.py
sigr/bnds.py
sigr/cons.py
sigr/deco.py
sigr/enum.py
sigr/grds.py
sigr/sigs.py
sigr/type.py
sigr/util.py
sigr-0.0.12.dist-info/LICENSE
sigr-0.0.12.dist-info/METADATA
sigr-0.0.12.dist-info/WHEEL
sigr-0.0.12.dist-info/entry_points.txt
sigr-0.0.12.dist-info/top_level.txt
sigr-0.0.12.dist-info/RECORD
